pyramid_notebook/__init__.py
pyramid_notebook/notebookmanager.py
pyramid_notebook/proxy.py
pyramid_notebook/startup.py
pyramid_notebook/utils.py
pyramid_notebook/uwsgi.py
pyramid_notebook/views.py
pyramid_notebook/demo/__init__.py
pyramid_notebook/demo/auth.py
pyramid_notebook/demo/development.ini
pyramid_notebook/demo/views.py
pyramid_notebook/demo/wsgi.py
pyramid_notebook/demo/templates/home.html
pyramid_notebook/demo/templates/login.html
pyramid_notebook/demo/templates/site/analytics.html
pyramid_notebook/demo/templates/site/base.html
pyramid_notebook/demo/templates/site/base_compact.html
pyramid_notebook/demo/templates/site/css.html
pyramid_notebook/demo/templates/site/description.html
pyramid_notebook/demo/templates/site/footer.html
pyramid_notebook/demo/templates/site/header.html
pyramid_notebook/demo/templates/site/javascript.html
pyramid_notebook/demo/templates/site/logo.html
pyramid_notebook/demo/templates/site/messages.html
pyramid_notebook/demo/templates/site/meta.html
pyramid_notebook/demo/templates/site/nav.html
pyramid_notebook/server/__init__.py
pyramid_notebook/server/comm.py
pyramid_notebook/server/custom.js
pyramid_notebook/server/notebook_daemon.py
pyramid_notebook-0.3.0.dist-info/LICENSE.txt
pyramid_notebook-0.3.0.dist-info/METADATA
pyramid_notebook-0.3.0.dist-info/WHEEL
pyramid_notebook-0.3.0.dist-info/entry_points.txt
pyramid_notebook-0.3.0.dist-info/top_level.txt
pyramid_notebook-0.3.0.dist-info/RECORD
