Metadata-Version: 2.1
Name: pyramid-notebook
Version: 0.3.0
Summary: Embed IPython Notebook shell on your Pyramid website
Home-page: https://github.com/websauna/pyramid_notebook
Author: Mikko Ohtamaa
Author-email: mikko@opensourcehacker.com
License: MIT
Keywords: ipython setuptools development shell uwsgi
Platform: UNKNOWN
Classifier: Development Status :: 3 - Alpha
Classifier: Intended Audience :: Developers
Classifier: Topic :: Software Development :: Build Tools
Classifier: Topic :: System :: Shells
Classifier: License :: OSI Approved :: MIT License
Classifier: Programming Language :: Python :: 3
Classifier: Programming Language :: Python :: 3.5
Classifier: Programming Language :: Python :: 3.6
Classifier: Programming Language :: Python :: 3.7
Classifier: Framework :: Pyramid
Classifier: Framework :: IPython
Requires-Python: >=3.5.2
Requires-Dist: ipython[notebook] (>=7.0.1)
Requires-Dist: daemonocle (>=1.0.1)
Requires-Dist: PasteDeploy
Requires-Dist: port-for
Requires-Dist: pyramid
Requires-Dist: sqlalchemy
Requires-Dist: ws4py
Provides-Extra: dev
Requires-Dist: flake8; extra == 'dev'
Requires-Dist: flake8-isort; extra == 'dev'
Requires-Dist: zest.releaser[recommended]; extra == 'dev'
Provides-Extra: test
Requires-Dist: codecov; extra == 'test'
Requires-Dist: flaky; extra == 'test'
Requires-Dist: paste; extra == 'test'
Requires-Dist: pyramid-jinja2; extra == 'test'
Requires-Dist: pytest; extra == 'test'
Requires-Dist: pytest-cov; extra == 'test'
Requires-Dist: pytest-splinter; extra == 'test'
Requires-Dist: selenium (>3); extra == 'test'
Requires-Dist: webtest; extra == 'test'
Provides-Extra: uwsgi
Requires-Dist: uwsgi; extra == 'uwsgi'
Requires-Dist: ws4py; extra == 'uwsgi'
